README.md
setup.cfg
setup.py
aiomihome/__init__.py
aiomihome/constants.py
aiomihome/gateway.py
aiomihome/helpers.py
aiomihome/service.py
aiomihome.egg-info/PKG-INFO
aiomihome.egg-info/SOURCES.txt
aiomihome.egg-info/dependency_links.txt
aiomihome.egg-info/not-zip-safe
aiomihome.egg-info/top_level.txt