Metadata-Version: 2.1
Name: aiomihome
Version: 1.0.4
Summary: Python asyncio implementation of Xiaomi Aqara Hub API
Home-page: https://github.com/egeback/aiomihome
Author: Marky Egebäck
Author-email: marky@egeback.se
License: MIT
Download-URL: https://github.com/egeback/aiomihome/archive/v1.0.3.zip
Keywords: xiaomi,aqara
Platform: any
Requires-Python: >=3.6.0
